dependencynet/__init__.py
dependencynet/data.py
dependencynet/datasets_utils.py
dependencynet/dependencynet.py
dependencynet/main.py
dependencynet/model.py
dependencynet/schema.py
dependencynet/tree_model.py
dependencynet/trees_utils.py
dependencynet/utils.py
dependencynet/datasource/__init__.py
dependencynet/datasource/core/__init__.py
dependencynet/datasource/core/encoders.py
dependencynet/datasource/core/levelsloader.py
dependencynet/datasource/core/modelprettyprinter.py
dependencynet/datasource/core/modelstorage.py
dependencynet/datasource/core/resourcesloader.py
dependencynet/datasource/loaders/__init__.py
dependencynet/datasource/loaders/levelsloader.py
dependencynet/datasource/loaders/resourcesloader.py
dependencynet/network/__init__.py
dependencynet/network/graphbuilder.py
dependencynet/network/graphml.py
dependencynet/network/graphviewer.py
dependencynet/network/stylebuilder.py
dependencynet-0.2.1.dist-info/LICENSE
dependencynet-0.2.1.dist-info/METADATA
dependencynet-0.2.1.dist-info/WHEEL
dependencynet-0.2.1.dist-info/top_level.txt
dependencynet-0.2.1.dist-info/RECORD
