Metadata-Version: 2.1
Name: dependencynet
Version: 0.2.1
Summary: This module wraps some data and graph manipulation tools to help analyzing and building representations of directed graphs.
Home-page: https://github.com/cfalguiere/dependencynet
Author: Claude Falguiere
Author-email: 
License: MIT
Platform: Any
Classifier: Development Status :: 3 - Alpha
Classifier: License :: OSI Approved :: MIT License
Classifier: Operating System :: OS Independent
Classifier: Programming Language :: Python
Requires-Python: >=3.7
Requires-Dist: pandas
Requires-Dist: networkx
Requires-Dist: ipycytoscape
Requires-Dist: pyyed
